pvc-export-etc/pvc export create config.desktop
pvc-export-etc/pvc export.desktop
pvc-export-etc/pvc-export.cmd
pvc-export-etc/requirements.txt
pvc-export-etc/win-install.reg
pvc_export/__init__.py
pvc_export/__main__.py
pvc_export/cfg.py
pvc_export/cli.py
pvc_export/config.py
pvc_export/data.py
pvc_export/main.py
pvc_export/mplrc.py
pvc_export/plot.py
pvc_export-0.0.1.2023.6.28.1635.dist-info/LICENSE.txt
pvc_export-0.0.1.2023.6.28.1635.dist-info/METADATA
pvc_export-0.0.1.2023.6.28.1635.dist-info/WHEEL
pvc_export-0.0.1.2023.6.28.1635.dist-info/entry_points.txt
pvc_export-0.0.1.2023.6.28.1635.dist-info/top_level.txt
pvc_export-0.0.1.2023.6.28.1635.dist-info/RECORD
