Metadata-Version: 2.1
Name: pvc-export
Version: 0.0.1.2023.6.28.1635
Summary: Export Implen NanoPhotometer P300 PVC wavescan (absorption spectrum) files into a PNG figure and CSV tables
Author: o124
License: Copyright (c) 2016 The Python Packaging Authority (PyPA)
Project-URL: Homepage, https://gitlab.com/_124_/pvc-export
Project-URL: Downloads, https://gitlab.com/_124_/pvc-export/-/packages
Keywords: Implen,NanoPhotometer,P300,pvc,export
Classifier: Development Status :: 4 - Beta
Classifier: License :: OSI Approved :: MIT License
Classifier: Programming Language :: Python :: 3
Requires-Python: >=3.8
License-File: LICENSE.txt
Requires-Dist: Pillow
Requires-Dist: PyYAML
Requires-Dist: scipy
Requires-Dist: matplotlib
